nonebot_plugin_group_config/__init__.py
nonebot_plugin_group_config/command.py
nonebot_plugin_group_config/config.py
nonebot_plugin_group_config/manager.py
nonebot_plugin_group_config/utils.py
nonebot_plugin_group_config-0.2.5.dist-info/licenses/LICENSE
nonebot_plugin_group_config-0.2.5.dist-info/METADATA
nonebot_plugin_group_config-0.2.5.dist-info/WHEEL
nonebot_plugin_group_config-0.2.5.dist-info/top_level.txt
nonebot_plugin_group_config-0.2.5.dist-info/RECORD
