Metadata-Version: 2.4
Name: nonebot_plugin_group_config
Version: 0.2.5
Summary: Nonebot2 群聊配置信息存储与管理插件
Requires-Python: <4.0,>=3.9
License-File: LICENSE
Requires-Dist: watchdog>=6.0.0
Requires-Dist: nonebot2>=2.3.0
Requires-Dist: nonebot-plugin-localstore>=0.7.0
Requires-Dist: nonebot-plugin-uninfo>=0.6.0
Dynamic: license-file
